MuBuild/ConfigValidator.py
MuBuild/MuBuild.py
MuBuild/__init__.py
mu_build-0.3.2.dist-info/LICENSE
mu_build-0.3.2.dist-info/METADATA
mu_build-0.3.2.dist-info/WHEEL
mu_build-0.3.2.dist-info/entry_points.txt
mu_build-0.3.2.dist-info/top_level.txt
mu_build-0.3.2.dist-info/RECORD
