Metadata-Version: 2.1
Name: mu-build
Version: 0.3.2
Summary: Supports CI build operations for Project Mu based firmware
Home-page: https://github.com/microsoft/mu_pip_build
Author: Project Mu Team
Author-email: maknutse@microsoft.com
License: BSD2
Platform: UNKNOWN
Classifier: Programming Language :: Python :: 3
Classifier: License :: OSI Approved :: BSD License
Classifier: Operating System :: OS Independent
Classifier: Development Status :: 4 - Beta
Requires-Dist: pyyaml
Requires-Dist: mu-environment (>=0.3.3)
Requires-Dist: mu-python-library (>=0.4.1)
